raptor/__init__.py
raptor/config.py
raptor/decorators.py
raptor/local_state.py
raptor/program.py
raptor/replay.py
raptor/windows.py
raptor/_internal/__init__.py
raptor/_internal/durpy.py
raptor/_internal/exporter/Makefile.j2
raptor/_internal/exporter/__init__.py
raptor/_internal/exporter/general.py
raptor/_internal/exporter/model.py
raptor/_internal/model_servers/__init__.py
raptor/_internal/model_servers/protocol.py
raptor/_internal/model_servers/sagemaker.py
raptor/_internal/model_servers/sagemaker/sagemaker_service.py
raptor/_internal/model_servers/sagemaker/serve
raptor/_internal/model_servers/sagemaker/template.j2
raptor/types/__init__.py
raptor/types/common.py
raptor/types/dsrc.py
raptor/types/feature.py
raptor/types/model.py
raptor/types/model_impl.py
raptor/types/primitives.py
raptor/types/yaml.py
raptor/types/dsrc_config_stubs/__init__.py
raptor/types/dsrc_config_stubs/protocol.py
raptor/types/dsrc_config_stubs/rest.py
raptor/types/dsrc_config_stubs/streaming.py
raptor_labsdk-0.3.2.dist-info/METADATA
raptor_labsdk-0.3.2.dist-info/WHEEL
raptor_labsdk-0.3.2.dist-info/top_level.txt
raptor_labsdk-0.3.2.dist-info/RECORD
