Metadata-Version: 2.1
Name: raptor-labsdk
Version: 0.3.2
Home-page: https://raptor.ml
Author: Almog Baku
Author-email: almog@raptor.ml
Project-URL: Documentation, https://raptor.ml/
Project-URL: Source, https://github.com/raptor-ml/raptor
Project-URL: Tracker, https://github.com/raptor-ml/raptor/issues
Classifier: Programming Language :: Python :: 3
Classifier: License :: OSI Approved :: Apache Software License
Classifier: Operating System :: OS Independent
Requires-Python: >=3.7, <4
Requires-Dist: pandas
Requires-Dist: redbaron >=0.9.2
Requires-Dist: typing-extensions
Requires-Dist: PyYAML >=5.0
Requires-Dist: pydantic
Requires-Dist: BentoML ==1.0.22
Requires-Dist: attrs >=21.1.0
Requires-Dist: Jinja2 >=3.1.0
